kalabash_amavis/__init__.py
kalabash_amavis/apps.py
kalabash_amavis/constants.py
kalabash_amavis/dbrouter.py
kalabash_amavis/factories.py
kalabash_amavis/forms.py
kalabash_amavis/handlers.py
kalabash_amavis/kbash_extension.py
kalabash_amavis/lib.py
kalabash_amavis/models.py
kalabash_amavis/settings.py
kalabash_amavis/sql_connector.py
kalabash_amavis/sql_email.py
kalabash_amavis/tasks.py
kalabash_amavis/test_runners.py
kalabash_amavis/urls.py
kalabash_amavis/utils.py
kalabash_amavis/views.py
kalabash_amavis/checks/__init__.py
kalabash_amavis/checks/settings_checks.py
kalabash_amavis/locale/cs_CZ/LC_MESSAGES/django.mo
kalabash_amavis/locale/cs_CZ/LC_MESSAGES/django.po
kalabash_amavis/locale/cs_CZ/LC_MESSAGES/djangojs.mo
kalabash_amavis/locale/cs_CZ/LC_MESSAGES/djangojs.po
kalabash_amavis/locale/de/LC_MESSAGES/django.mo
kalabash_amavis/locale/de/LC_MESSAGES/django.po
kalabash_amavis/locale/de/LC_MESSAGES/djangojs.mo
kalabash_amavis/locale/de/LC_MESSAGES/djangojs.po
kalabash_amavis/locale/el_GR/LC_MESSAGES/django.mo
kalabash_amavis/locale/el_GR/LC_MESSAGES/django.po
kalabash_amavis/locale/el_GR/LC_MESSAGES/djangojs.mo
kalabash_amavis/locale/el_GR/LC_MESSAGES/djangojs.po
kalabash_amavis/locale/en/LC_MESSAGES/django.mo
kalabash_amavis/locale/en/LC_MESSAGES/django.po
kalabash_amavis/locale/en/LC_MESSAGES/djangojs.mo
kalabash_amavis/locale/en/LC_MESSAGES/djangojs.po
kalabash_amavis/locale/es/LC_MESSAGES/django.mo
kalabash_amavis/locale/es/LC_MESSAGES/django.po
kalabash_amavis/locale/es/LC_MESSAGES/djangojs.mo
kalabash_amavis/locale/es/LC_MESSAGES/djangojs.po
kalabash_amavis/locale/fr/LC_MESSAGES/django.mo
kalabash_amavis/locale/fr/LC_MESSAGES/django.po
kalabash_amavis/locale/fr/LC_MESSAGES/djangojs.mo
kalabash_amavis/locale/fr/LC_MESSAGES/djangojs.po
kalabash_amavis/locale/it/LC_MESSAGES/django.mo
kalabash_amavis/locale/it/LC_MESSAGES/django.po
kalabash_amavis/locale/it/LC_MESSAGES/djangojs.mo
kalabash_amavis/locale/it/LC_MESSAGES/djangojs.po
kalabash_amavis-1.5.2.dist-info/LICENSE
kalabash_amavis-1.5.2.dist-info/METADATA
kalabash_amavis-1.5.2.dist-info/WHEEL
kalabash_amavis-1.5.2.dist-info/top_level.txt
kalabash_amavis-1.5.2.dist-info/RECORD
